ipyhtmx/__init__.py
ipyhtmx/_version.py
ipyhtmx/htmx.py
ipyhtmx/labextension/package.json
ipyhtmx/labextension/static/16.6802e8ac1439f5ec1629.js
ipyhtmx/labextension/static/261.82b77da9ce56d0f1adfe.js
ipyhtmx/labextension/static/28.9c94b7dffc11e1d4a076.js
ipyhtmx/labextension/static/remoteEntry.0e82e021456e825ad97a.js
ipyhtmx/labextension/static/style.js
ipyhtmx/labextension/static/third-party-licenses.json
ipyhtmx/nbextension/extension.js
ipyhtmx/nbextension/index.js
ipyhtmx-0.1.0.data/data/etc/jupyter/nbconfig/notebook.d/ipyhtmx.json
ipyhtmx-0.1.0.data/data/share/jupyter/labextensions/ipyhtmx/install.json
ipyhtmx-0.1.0.data/data/share/jupyter/labextensions/ipyhtmx/package.json
ipyhtmx-0.1.0.data/data/share/jupyter/labextensions/ipyhtmx/static/16.6802e8ac1439f5ec1629.js
ipyhtmx-0.1.0.data/data/share/jupyter/labextensions/ipyhtmx/static/261.82b77da9ce56d0f1adfe.js
ipyhtmx-0.1.0.data/data/share/jupyter/labextensions/ipyhtmx/static/28.9c94b7dffc11e1d4a076.js
ipyhtmx-0.1.0.data/data/share/jupyter/labextensions/ipyhtmx/static/remoteEntry.0e82e021456e825ad97a.js
ipyhtmx-0.1.0.data/data/share/jupyter/labextensions/ipyhtmx/static/style.js
ipyhtmx-0.1.0.data/data/share/jupyter/labextensions/ipyhtmx/static/third-party-licenses.json
ipyhtmx-0.1.0.data/data/share/jupyter/nbextensions/ipyhtmx/extension.js
ipyhtmx-0.1.0.data/data/share/jupyter/nbextensions/ipyhtmx/index.js
ipyhtmx-0.1.0.dist-info/METADATA
ipyhtmx-0.1.0.dist-info/WHEEL
ipyhtmx-0.1.0.dist-info/top_level.txt
ipyhtmx-0.1.0.dist-info/RECORD
